[
  {
    "id": 1,
    "image": "https://www.blogdelfotografo.com/wp-content/uploads/2014/09/Libro-Retrato.jpg",
    "full_name": "Marillin Pooley",
    "email": "mpooley0@webmd.com",
    "contact": "7606502819",
    "description": "Speech Pathologist",
    "start_date": "05/09/2022",
    "status": false,
    "password": "7uPl3CenJya"
  },
  {
    "id": 2,
    "image": "https://img.freepik.com/fotos-premium/retrato-guapo-sonriente-estilo-hipster-lambersexual-modelo-sexy-hombre-vestido-camiseta-rosa-pantalones-hombre-moda-aislado-pared-azul-estudio_158538-26678.jpg",
    "full_name": "Kent Gooden",
    "email": "kgooden1@paypal.com",
    "contact": "1551613228",
    "description": "Junior Executive",
    "start_date": "31/01/2022",
    "status": false,
    "password": "I4Vim7"
  },
  {
    "id": 3,
    "image": "https://fototrending.com/wp-content/uploads/retratos-fotograficos-artisticos.jpg",
    "full_name": "Georgeanne Kennermann",
    "email": "gkennermann2@wp.com",
    "contact": "4393686551",
    "description": "Help Desk Operator",
    "start_date": "27/03/2022",
    "status": true,
    "password": "XmP62JZPMwmd"
  },
  {
    "id": 4,
    "image": "https://i.blogs.es/447a66/joeyl_02/450_1000.jpg",
    "full_name": "Annice McPhail",
    "email": "amcphail3@infoseek.co.jp",
    "contact": "7534558227",
    "description": "Senior Cost Accountant",
    "start_date": "07/04/2022",
    "status": true,
    "password": "0cLEsZ5Th"
  },
  {
    "id": 5,
    "image": "https://img.freepik.com/foto-gratis/winsome-hermosa-joven-posando-pared-marron-toma-primer-plano-maravillosa-chica-morena_197531-13994.jpg",
    "full_name": "Emelita Boar",
    "email": "eboar4@cloudflare.com",
    "contact": "2471039426",
    "description": "Programmer Analyst I",
    "start_date": "22/02/2022",
    "status": true,
    "password": "l3TCyq9C3XK"
  },
  {
    "id": 6,
    "image": "https://img.freepik.com/foto-gratis/retrato-mujer-caucasica-sonriendo_53876-24998.jpg",
    "full_name": "Buiron Le Pine",
    "email": "ble5@altervista.org",
    "contact": "9322774113",
    "description": "Environmental Specialist",
    "start_date": "21/02/2022",
    "status": true,
    "password": "xNmJYHQ"
  },
  {
    "id": 7,
    "image": "https://img.freepik.com/foto-gratis/closeup-retrato-mujer-hermosa-maquillaje-brillante-rojas-chica-adulta-joven-sexy-lapiz-labial-rojo_186202-8397.jpg",
    "full_name": "Sandy Flanagan",
    "email": "sflanagan6@eventbrite.com",
    "contact": "2311874326",
    "description": "Community Outreach Specialist",
    "start_date": "07/09/2022",
    "status": true,
    "password": "uEV4QCs7KCu"
  },
  {
    "id": 8,
    "image": "https://mott.pe/noticias/wp-content/uploads/2018/07/uno-de-los-errores-de-la-fotografia-de-retrato-es-no-calcular-el-balance-de-blancos.png",
    "full_name": "Wallache Wigglesworth",
    "email": "wwigglesworth7@oakley.com",
    "contact": "9418239750",
    "description": "Nurse",
    "start_date": "12/05/2022",
    "status": false,
    "password": "FtwsnXaL2"
  },
  {
    "id": 9,
    "image": "https://lh3.googleusercontent.com/-CVSScpWOKf8/WEreasxe2nI/AAAAAAAAz2w/wRxjn1pOm0o/image_thumb%25255B1%25255D.png?imgmax=800",
    "full_name": "Fairlie Klaus",
    "email": "fklaus8@mayoclinic.com",
    "contact": "7993794977",
    "description": "Tax Accountant",
    "start_date": "29/11/2021",
    "status": false,
    "password": "Pid4ve"
  },
  {
    "id": 10,
    "image": "https://fototrending.com/wp-content/uploads/retrato-en-blanco-y-negro.jpg",
    "full_name": "Egbert Weedon",
    "email": "eweedon9@nymag.com",
    "contact": "8039253084",
    "description": "Help Desk Operator",
    "start_date": "02/10/2022",
    "status": true,
    "password": "bZcF3V4"
  }
]

